{
  "id": "fin-resolve-expense-dispute",
  "name": "Resolve employee expense claim dispute",
  "description": "Resolve dispute where employee challenges rejected expense claim with review and final decision",
  "task": "RESOLVE",
  "dom": "FIN",
  "packet": "RESOLVE|FIN|return:FIN-Agent|p:2|aacp:1.1|res:expense_dispute|req:policy_review,manager_confirm,final_decision",
  "tags": [
    "expense",
    "dispute",
    "resolution",
    "finance"
  ],
  "version": "1.1",
  "source": "community",
  "validated": true
}